contactbook/__init__.py
contactbook/main.py
tests/__init__.py
contactbook-1.1.4.dist-info/LICENSE
contactbook-1.1.4.dist-info/METADATA
contactbook-1.1.4.dist-info/WHEEL
contactbook-1.1.4.dist-info/entry_points.txt
contactbook-1.1.4.dist-info/top_level.txt
contactbook-1.1.4.dist-info/RECORD
